.DS_Store
yaplon/__init__.py
yaplon/__main__.py
yaplon/ojson.py
yaplon/oplist.py
yaplon/oyaml.py
yaplon/reader.py
yaplon/writer.py
yaplon/file_strip/__init__.py
yaplon/file_strip/comments.py
yaplon/file_strip/json.py
yaplon-1.6.0.dist-info/LICENSE
yaplon-1.6.0.dist-info/METADATA
yaplon-1.6.0.dist-info/WHEEL
yaplon-1.6.0.dist-info/entry_points.txt
yaplon-1.6.0.dist-info/top_level.txt
yaplon-1.6.0.dist-info/RECORD
