Metadata-Version: 2.1
Name: yaplon
Version: 1.6.0
Summary: Python 3-based commandline converter CSV → YAML ↔ JSON ↔ PLIST ↔ XML
Home-page: https://twardoch.github.io/yaplon/
Author: Adam Twardoch
Author-email: adam+github@twardoch.com
License: MIT
Project-URL: Source, https://github.com/twardoch/yaplon/
Keywords: yaml json plist csv xml convert cli
Classifier: Environment :: Console
Classifier: Development Status :: 4 - Beta
Classifier: License :: OSI Approved :: MIT License
Classifier: Programming Language :: Python :: 3.9
Requires-Python: >=3.9
License-File: LICENSE
Requires-Dist: PyYAML (>=5.4.1)
Requires-Dist: click (>=7.1.2)
Requires-Dist: dict2xml (>=1.7.0)
Requires-Dist: orderedattrdict (>=1.6.0)
Requires-Dist: xmltodict (>=0.12.0)
Provides-Extra: dev
Requires-Dist: setuptools ; extra == 'dev'
Requires-Dist: wheel ; extra == 'dev'
Requires-Dist: pip ; extra == 'dev'
Requires-Dist: twine (>=3.2.0) ; extra == 'dev'
Requires-Dist: pyinstaller (>=4.0) ; extra == 'dev'
